MANIFEST.in
README.md
requirements.txt
setup.cfg
setup.py
gundala/__init__.py
gundala/templates/__init__.py
gundala/templates/contact.py
gundala/templates/domain.py