Metadata-Version: 1.1
Name: gundala
Version: 0.1.9
Summary: Gundala Python EPP client
Home-page: https://github.com/BiznetGIO
Author: BiznetGio
Author-email: support@biznetgio.com
License: MIT
Keywords: epp
Platform: UNKNOWN
Classifier: Intended Audience :: Developers
Classifier: Topic :: Utilities
Classifier: License :: Public Domain
Classifier: Natural Language :: English
Classifier: Operating System :: OS Independent
Classifier: Programming Language :: Python :: 3
Classifier: Programming Language :: Python :: 3.2
Classifier: Programming Language :: Python :: 3.3
Classifier: Programming Language :: Python :: 3.4
Classifier: Programming Language :: Python :: 3.5
Classifier: Programming Language :: Python :: 3.6
